[
  {
    "title": "Home",
    "path": "/",
    "dropdown": false
  },

  {
    "title": "Product Category",
    "path": "#",
    "dropdown": true,
    "items": [
      {
        "title": "Herbal Oil",
        "path": "/herbal-oil"
      },
      {
        "title": "Hair Care",
        "path": "/hair-care"
      },
      {
        "title": "Skin Care",
        "path": "/skin-care"
      },
      {
        "title": "Winter Care",
        "path": "/winter-care"
      },
      {
        "title": "Color Cosmetics",
        "path": "/color-cosmetics"
      },
      {
        "title": "Fragrances",
        "path": "/fragrances"
      }
    ]
  },
  {
    "title": "Featured Products",
    "path": "/featured-products",
    "dropdown": false
  },
  {
    "title": "About Us",
    "path": "/about",
    "dropdown": false
  },
  {
    "title": "Contact Us",
    "path": "/contact",
    "dropdown": false
  }
]
